donerkebab/__init__.py
donerkebab/_spinner.py
donerkebab/_utils.py
donerkebab/driver.py
donerkebab/init_driver.py
donerkebab/keys.py
donerkebab-0.0.2.dist-info/LICENSE
donerkebab-0.0.2.dist-info/METADATA
donerkebab-0.0.2.dist-info/WHEEL
donerkebab-0.0.2.dist-info/top_level.txt
donerkebab-0.0.2.dist-info/RECORD
