Metadata-Version: 2.1
Name: donerkebab
Version: 0.0.2
Summary: Super easy to use selenium wrapper
Home-page: https://github.com/ytkimirti/donerkebab
Author: ytkimirti
Author-email: yusuftaha9@gmail.com
License: MIT
Keywords: selenium,wrapper,chrome,firefox,easy,beginner,use,doner,kebab,chromium,headless
Platform: UNKNOWN
Classifier: Programming Language :: Python
Classifier: Programming Language :: Python :: 3.6
Classifier: Programming Language :: Python :: 3.7
Classifier: Programming Language :: Python :: 3.8
Requires-Python: >=3.6
Requires-Dist: selenium (>=4.1.0)
Requires-Dist: halo (>=0.0.31)
